{
    "persons": {
        "Alicia": {
            "birth": {
                "ETERNITY": "1980-01-01"
            },
            "所得": {
                "2017-01": 4000
            },
            "可処分所得": {
                "2017-01": null
            }
        },
        "Javier": {
            "birth": {
                "ETERNITY": "1984-01-01"
            },
            "所得": {
                "2017-01": 2500
            },
            "可処分所得": {
                "2017-01": null
            }
        }
    },
    "households": {
        "_": {
            "parents": ["Alicia", "Javier"],
            "total_benefits": {
                "2017-01": null
            },
            "total_taxes": {
                "2017-01": null
            }
        }
    }
}
